mesa/__init__.py
mesa/archive/figure2_related_analysis/multiomics_matching_tonsil.ipynb
mesa/archive/figure2_related_analysis/neighborhood_GSEA.R
mesa/archive/figure2_related_analysis/neighborhood_clustering.ipynb
mesa/archive/figure2_related_analysis/neighborhood_differential_expression.R
mesa/archive/figure3_related_analysis/package_demo_mouse.ipynb
mesa/archive/figure4_related_analysis/hotspot_differential_expression.R
mesa/archive/figure4_related_analysis/multiomics_matching_CRC_B_cell.ipynb
mesa/archive/figure4_related_analysis/multiomics_matching_CRC_macrophage.ipynb
mesa/archive/figure4_related_analysis/package_demo_crc.ipynb
mesa/archive/figure5_related_analysis/liver_communication.ipynb
mesa/archive/figure5_related_analysis/liver_scrna_dataprep.ipynb
mesa/archive/figure5_related_analysis/package_demo_liver.ipynb
mesa/archive/others/additional_crc.ipynb
mesa/archive/others/additional_liver.ipynb
mesa/archive/others/additional_mouse.ipynb
mesa/archive/others/clustering_benchmark_results.ipynb
mesa/archive/others/clustering_fsom.R
mesa/archive/others/neighborhood_clustering_compare.ipynb
mesa/archive/others/neighborhood_clustering_second_rnaseq.ipynb
mesa/archive/others/synthetic_data_benchmarking.ipynb
mesa/archive/others/synthetic_data_mesa.ipynb
mesa/ecospatial/__init__.py
mesa/ecospatial/_ecospatial.py
mesa/ecospatial/_pl.py
mesa/ecospatial/_utils.py
mesa/multiomics/__init__.py
mesa/multiomics/multiomics_fusion/multiomics_fusion_tutorial.ipynb
mesa/multiomics/multiomics_fusion/multiomics_matching_CRC.ipynb
mesa/multiomics/multiomics_fusion/multiomics_matching_CRC_B_cell.ipynb
mesa/multiomics/multiomics_fusion/multiomics_matching_CRC_macrophage.ipynb
mesa/multiomics/multiomics_fusion/multiomics_matching_tonsil.ipynb
mesa/multiomics/multiomics_spatial/__init__.py
mesa/multiomics/multiomics_spatial/graph.py
mesa/multiomics/multiomics_spatial/hotspot_differential_expression.R
mesa/multiomics/multiomics_spatial/neighborhood_GSEA.R
mesa_py-0.1.2.dist-info/METADATA
mesa_py-0.1.2.dist-info/WHEEL
mesa_py-0.1.2.dist-info/licenses/LICENSE
mesa_py-0.1.2.dist-info/RECORD
