Metadata-Version: 2.1
Name: mesa-py
Version: 0.1.2
Summary: Multiomics and Ecological Spatial Analysis for Quantitative Decoding of Cellular Neighborhoods and Tissue Compartments
Project-URL: Homepage, https://github.com/feanor007/mesa
Project-URL: Issues, https://github.com/feanor007/mesa/issues
Author-email: Daisy Yi Ding <dingd@stanford.edu>, Zeyu Tang <feanortang@gmail.com>, Bokai Zhu <bkzhu@stanford.edu>
Maintainer-email: Zeyu Tang <feanortang@gmail.com>
License-File: LICENSE
Classifier: Operating System :: OS Independent
Classifier: Programming Language :: Python :: 3
Requires-Python: >=3.10
Requires-Dist: anndata
Requires-Dist: igraph
Requires-Dist: leidenalg
Requires-Dist: matplotlib
Requires-Dist: networkx
Requires-Dist: numpy
Requires-Dist: pandas
Requires-Dist: pysal
Requires-Dist: scipy
Requires-Dist: seaborn
Provides-Extra: docs
Requires-Dist: sphinx-rtd-theme; extra == 'docs'
Requires-Dist: sphinx>=5.3; extra == 'docs'
